modeling/__init__.py
modeling/hyperopt_tuner.py
modeling/model_trainer.py
modeling/optuna_tuner.py
modeling_5632425-0.1.1.dist-info/METADATA
modeling_5632425-0.1.1.dist-info/WHEEL
modeling_5632425-0.1.1.dist-info/entry_points.txt
modeling_5632425-0.1.1.dist-info/RECORD
