Metadata-Version: 2.4
Name: modeling_5632425
Version: 0.1.1
Summary: Hyperparameter optimization and validation tools
Author: Katsiaryna
Author-email: katsiaryna.shymchonak@innowise.com
Requires-Python: >=3.12
Classifier: Programming Language :: Python :: 3
Classifier: Programming Language :: Python :: 3.12
Classifier: Programming Language :: Python :: 3.13
Classifier: Programming Language :: Python :: 3.14
Requires-Dist: dill
Requires-Dist: hyperopt
Requires-Dist: numpy
Requires-Dist: optuna
Requires-Dist: pandas
Requires-Dist: scikit-learn
